offlinedatasci/__init__.py
offlinedatasci/cli.py
offlinedatasci/main.py
offlinedatasci/miniCran.R
offlinedatasci-0.7.0.dist-info/LICENSE
offlinedatasci-0.7.0.dist-info/METADATA
offlinedatasci-0.7.0.dist-info/WHEEL
offlinedatasci-0.7.0.dist-info/entry_points.txt
offlinedatasci-0.7.0.dist-info/top_level.txt
offlinedatasci-0.7.0.dist-info/RECORD
