Metadata-Version: 2.1
Name: offlinedatasci
Version: 0.7.0
Summary: Download and configure common tools for teaching and doing data science without an internet connection
Author: Virnaliz Cruz, Colin Sauze, Jannetta Steyn, Abhishek Dasgupta, Ethan P. White
Project-URL: Carpentries Offline Website, https://carpentriesoffline.github.io/
Project-URL: Documentation, https://github.com/carpentriesoffline/offlinedatasci/#readme
Project-URL: CI, https://github.com/carpentriesoffline/offlinedatasci/actions
Project-URL: Source, https://github.com/carpentriesoffline/offlinedatasci
Project-URL: Tracker, https://github.com/carpentriesoffline/offlinedatasci/issues
Classifier: Development Status :: 3 - Alpha
Classifier: Environment :: Console
Classifier: Environment :: Win32 (MS Windows)
Classifier: Intended Audience :: Education
Classifier: Intended Audience :: Science/Research
Classifier: License :: OSI Approved :: MIT License
Classifier: Natural Language :: English
Classifier: Operating System :: POSIX :: Linux
Classifier: Operating System :: MacOS :: MacOS X
Classifier: Operating System :: Microsoft :: Windows
Classifier: Programming Language :: Python :: 3
Classifier: Programming Language :: Python :: 3.6
Classifier: Programming Language :: Python :: 3.7
Classifier: Programming Language :: Python :: 3.8
Classifier: Programming Language :: Python :: 3.9
Classifier: Programming Language :: Python :: 3.10
Classifier: Topic :: Education
Classifier: Topic :: Scientific/Engineering
Requires-Python: >=3.6
License-File: LICENSE
Requires-Dist: airium
Requires-Dist: beautifulsoup4
Requires-Dist: importlib-resources
Requires-Dist: lxml
Requires-Dist: python-pypi-mirror
Requires-Dist: requests
Requires-Dist: setuptools
